Metadata-Version: 2.1
Name: exceltpl
Version: 0.0.1
Summary: generate xlsx file with jinja2 template
Home-page: https://github.com/kalavt/exceltpl
Author: kalavt
Author-email: unknow@unknow.com
License: UNKNOWN
Platform: UNKNOWN
License-File: LICENSE
